pylegs/__init__.py
pylegs/archive.py
pylegs/cli.py
pylegs/config.py
pylegs/cutout.py
pylegs/io.py
pylegs/pixscale.py
pylegs/tap.py
pylegs/utils.py
pylegs/cli/axmatch.yaml
pylegs/cli/cutout.yaml
pylegs/cli/dlcat.yaml
pylegs/cli/drop.yaml
pylegs/cli/ls.yaml
pylegs/cli/pldrop.yaml
pylegs/cli/xmatch.yaml
pylegs/data/correction_factor.dat
pylegs/data/correction_factor_old.dat
pylegs/tests/__init__.py
pylegs/tests/test_utils.py
pylegs-0.4.11.dist-info/METADATA
pylegs-0.4.11.dist-info/WHEEL
pylegs-0.4.11.dist-info/entry_points.txt
pylegs-0.4.11.dist-info/top_level.txt
pylegs-0.4.11.dist-info/RECORD
